cploy/__init__.py
cploy/com.py
cploy/cploy.py
cploy/exceptions.py
cploy/fsmon.py
cploy/log.py
cploy/manager.py
cploy/message.py
cploy/sftp.py
cploy/task.py
cploy/worker.py
cploy-0.6.4.dist-info/LICENSE.txt
cploy-0.6.4.dist-info/METADATA
cploy-0.6.4.dist-info/RECORD
cploy-0.6.4.dist-info/WHEEL
cploy-0.6.4.dist-info/entry_points.txt
cploy-0.6.4.dist-info/top_level.txt
