Metadata-Version: 2.1
Name: cploy
Version: 0.6.4
Summary: The ad hoc continuous deployment solution for developers
Home-page: https://github.com/deadc0de6/cploy
Author: deadc0de6
Author-email: deadc0de6@foo.bar
License: GPLv3
Download-URL: https://github.com/deadc0de6/cploy/archive/v0.6.4.tar.gz
Keywords: continuous deployment cli
Platform: UNKNOWN
Classifier: Development Status :: 5 - Production/Stable
Classifier: Programming Language :: Python :: 3.5
Classifier: Programming Language :: Python :: 3.6
Classifier: License :: OSI Approved :: GNU General Public License v3 (GPLv3)
Provides-Extra: test
Provides-Extra: dev
Requires-Dist: docopt
Requires-Dist: paramiko
Requires-Dist: pyinotify
Requires-Dist: python-daemon
Provides-Extra: dev
Requires-Dist: check-manifest; extra == 'dev'
Provides-Extra: test
Requires-Dist: coverage; extra == 'test'
Requires-Dist: pytest; extra == 'test'
Requires-Dist: pytest-cov; extra == 'test'
